valguard/__init__.py
valguard/constrained_dict.py
valguard/constraints.py
valguard/core.py
valguard/exceptions.py
valguard/py.typed
valguard-1.0.1.dist-info/LICENSE
valguard-1.0.1.dist-info/METADATA
valguard-1.0.1.dist-info/WHEEL
valguard-1.0.1.dist-info/RECORD
