Metadata-Version: 2.3
Name: valguard
Version: 1.0.1
Summary: valguard: A lightweight framework for defining and validating values in data pipelines.
License: Apache-2.0
Keywords: data,validation,values,constraints,pipelines
Author: Jonathan Manton
Author-email: j.manton@ieee.org
Requires-Python: >=3.12,<4.0
Classifier: License :: OSI Approved :: Apache Software License
Classifier: Programming Language :: Python :: 3
Classifier: Programming Language :: Python :: 3.12
Classifier: Programming Language :: Python :: 3.13
Project-URL: Homepage, https://github.com/jhmanton/valguard
Project-URL: Repository, https://github.com/jhmanton/valguard
